Workbook

Sheet NSE
A1: instrument_token | B1: exchange_token | C1: tradingsymbol | D1: name | E1: last_price | F1: expiry | G1: strike | H1: tick_size | I1: lot_size | J1: instrument_type | K1: segment | L1: exchange | M1: GOLD | N1: name | O1: nav
A2: 256265 | B2: 1001 | C2: NIFTY 50 | D2: NIFTY 50 | E2: 0 | G2: 0 | H2: 0 | I2: 0 | J2: EQ | K2: INDICES | L2: NSE
A3: 256777 | B3: 1003 | C3: NIFTY MIDCAP 100 | D3: NIFTY MIDCAP 100 | E3: 0 | G3: 0 | H3: 0 | I3: 0 | J3: EQ | K3: INDICES | L3: NSE
A4: 260105 | B4: 1016 | C4: NIFTY BANK | D4: NIFTY BANK | E4: 0 | G4: 0 | H4: 0 | I4: 0 | J4: EQ | K4: INDICES | L4: NSE
A5: 260617 | B5: 1018 | C5: NIFTY 100 | D5: NIFTY 100 | E5: 0 | G5: 0 | H5: 0 | I5: 0 | J5: EQ | K5: INDICES | L5: NSE
A6: 257033 | B6: 1004 | C6: NIFTY DIV OPPS 50 | D6: NIFTY DIV OPPS 50 | E6: 0 | G6: 0 | H6: 0 | I6: 0 | J6: EQ | K6: INDICES | L6: NSE
A7: 257289 | B7: 1005 | C7: NIFTY COMMODITIES | D7: NIFTY COMMODITIES | E7: 0 | G7: 0 | H7: 0 | I7: 0 | J7: EQ | K7: INDICES | L7: NSE
A8: 257545 | B8: 1006 | C8: NIFTY CONSUMPTION | D8: NIFTY CONSUMPTION | E8: 0 | G8: 0 | H8: 0 | I8: 0 | J8: EQ | K8: INDICES | L8: NSE
A9: 257801 | B9: 1007 | C9: NIFTY FIN SERVICE | D9: NIFTY FIN SERVICE | E9: 0 | G9: 0 | H9: 0 | I9: 0 | J9: EQ | K9: INDICES | L9: NSE
A10: 258825 | B10: 1011 | C10: NIFTY50 PR 2X LEV | D10: NIFTY50 PR 2X LEV | E10: 0 | G10: 0 | H10: 0 | I10: 0 | J10: EQ | K10: INDICES | L10: NSE
A11: 259081 | B11: 1012 | C11: NIFTY50 PR 1X INV | D11: NIFTY50 PR 1X INV | E11: 0 | G11: 0 | H11: 0 | I11: 0 | J11: EQ | K11: INDICES | L11: NSE
A12: 259337 | B12: 1013 | C12: NIFTY50 TR 2X LEV | D12: NIFTY50 TR 2X LEV | E12: 0 | G12: 0 | H12: 0 | I12: 0 | J12: EQ | K12: INDICES | L12: NSE
A13: 259593 | B13: 1014 | C13: NIFTY50 TR 1X INV | D13: NIFTY50 TR 1X INV | E13: 0 | G13: 0 | H13: 0 | I13: 0 | J13: EQ | K13: INDICES | L13: NSE
... A177: 36865 | B177: 144 | C177: GODREJAGRO | D177: GODREJ AGROVET | E177: 0 | G177: 0 | H177: 0.05 | I177: 1 | J177: EQ | K177: NSE | L177: NSE
A178: 38145 | B178: 149 | C178: SGBSEP28VI-GB | D178: 2.50%GOLDBONDS2028SR-VI | E178: 0 | G178: 0 | H178: 0.01 | I178: 1 | J178: EQ | K178: NSE | L178: NSE | M178: Yes
A179: 39425 | B179: 154 | C179: APCOTEXIND | D179: APCOTEX INDUSTRIES LIMITE | E179: 0 | G179: 0 | H179: 0.05 | I179: 1 | J179: EQ | K179: NSE | L179: NSE
A180: 40193 | B180: 157 | C180: APOLLOHOSP | D180: APOLLO HOSPITALS ENTER. L | E180: 0 | G180: 0 | H180: 0.5 | I180: 1 | J180: EQ | K180: NSE | L180: NSE
A181: 40449 | B181: 158 | C181: 67MH28-SG | D181: SDL MH 6.7% 2028 | E181: 0 | G181: 0 | H181: 0.01 | I181: 100 | J181: EQ | K181: NSE | L181: NSE
A182: 41217 | B182: 161 | C182: 674UP30-SG | D182: SDL UP 6.74% 2030 | E182: 0 | G182: 0 | H182: 0.01 | I182: 100 | J182: EQ | K182: NSE | L182: NSE
A183: 41473 | B183: 162 | C183: MILTON-ST | D183: MILTON INDUSTRIES | E183: 0 | G183: 0 | H183: 0.05 | I183: 4400 | J183: EQ | K183: NSE | L183: NSE
A184: 41729 | B184: 163 | C184: APOLLOTYRE | D184: APOLLO TYRES | E184: 0 | G184: 0 | H184: 0.05 | I184: 1 | J184: EQ | K184: NSE | L184: NSE
A185: 41985 | B185: 164 | C185: 68AS30-SG | D185: SDL AS 6.8% 2030 | E185: 0 | G185: 0 | H185: 0.01 | I185: 100 | J185: EQ | K185: NSE | L185: NSE
A186: 42241 | B186: 165 | C186: 674GA30-SG | D186: SDL GA 6.74% 2030 | E186: 0 | G186: 0 | H186: 0.01 | I186: 100 | J186: EQ | K186: NSE | L186: NSE
A187: 42497 | B187: 166 | C187: ANDHRAPAP | D187: ANDHRA PAPER | E187: 0 | G187: 0 | H187: 0.01 | I187: 1 | J187: EQ | K187: NSE | L187: NSE
A188: 42753 | B188: 167 | C188: 67GJ30-SG | D188: SDL GJ 6.7% 2030 | E188: 0 | G188: 0 | H188: 0.01 | I188: 100 | J188: EQ | K188: NSE | L188: NSE
A189: 43521 | B189: 170 | C189: 67KA30-SG | D189: SDL KA 6.7% 2030 | E189: 0 | G189: 0 | H189: 0.01 | I189: 100 | J189: EQ | K189: NSE | L189: NSE
A190: 43777 | B190: 171 | C190: 672RJ30-SG | D190: SDL RJ 6.72% 2030 | E190: 0 | G190: 0 | H190: 0.01 | I190: 100 | J190: EQ | K190: NSE | L190: NSE
... A196: 47361 | B196: 185 | C196: 678MH32-SG | D196: SDL MH 6.78% 2032 | E196: 0 | G196: 0 | H196: 0.01 | I196: 100 | J196: EQ | K196: NSE | L196: NSE
A197: 47617 | B197: 186 | C197: 850NHAI29-N5 | E197: 0 | G197: 0 | H197: 0.01 | I197: 1 | J197: EQ | K197: NSE | L197: NSE | N197: blank
A198: 49153 | B198: 192 | C198: 875NHAI29-N6 | E198: 0 | G198: 0 | H198: 0.01 | I198: 1 | J198: EQ | K198: NSE | L198: NSE | N198: blank
A199: 49409 | B199: 193 | C199: ARVIND | D199: ARVIND | E199: 0 | G199: 0 | H199: 0.05 | I199: 1 | J199: EQ | K199: NSE | L199: NSE
A200: 50945 | B200: 199 | C200: MASFIN | D200: MAS FINANCIAL SERV | E200: 0 | G200: 0 | H200: 0.05 | I200: 1 | J200: EQ | K200: NSE | L200: NSE
A201: 51457 | B201: 201 | C201: UNIDT | D201: UNITED DRILLING TOOLS | E201: 0 | G201: 0 | H201: 0.01 | I201: 1 | J201: EQ | K201: NSE | L201: NSE
A202: 51969 | B202: 203 | C202: ASHAPURMIN | D202: ASHAPURA MINECHEM | E202: 0 | G202: 0 | H202: 0.05 | I202: 1 | J202: EQ | K202: NSE | L202: NSE
A203: 52737 | B203: 206 | C203: ASHIMASYN | D203: ASHIMA | E203: 0 | G203: 0 | H203: 0.01 | I203: 1 | J203: EQ | K203: NSE | L203: NSE
A204: 54273 | B204: 212 | C204: ASHOKLEY | D204: ASHOK LEYLAND | E204: 0 | G204: 0 | H204: 0.01 | I204: 1 | J204: EQ | K204: NSE | L204: NSE
A205: 56321 | B205: 220 | C205: IEX | D205: INDIAN ENERGY EXC | E205: 0 | G205: 0 | H205: 0.01 | I205: 1 | J205: EQ | K205: NSE | L205: NSE
A206: 60161 | B206: 235 | C206: AAKASH | D206: AAKASH EXPLORATION SER L | E206: 0 | G206: 0 | H206: 0.01 | I206: 1 | J206: EQ | K206: NSE | L206: NSE
A207: 60417 | B207: 236 | C207: ASIANPAINT | D207: ASIAN PAINTS | E207: 0 | G207: 0 | H207: 0.1 | I207: 1 | J207: EQ | K207: NSE | L207: NSE
A208: 62721 | B208: 245 | C208: ADL | D208: ARCHIDPLY DECOR | E208: 0 | G208: 0 | H208: 0.01 | I208: 1 | J208: EQ | K208: NSE | L208: NSE
A209: 65281 | B209: 255 | C209: NIRAJ | D209: NIRAJ CEMENT STRUC | E209: 0 | G209: 0 | H209: 0.01 | I209: 1 | J209: EQ | K209: NSE | L209: NSE
A210: 67329 | B210: 263 | C210: ATUL | D210: ATUL | E210: 0 | G210: 0 | H210: 0.5 | I210: 1 | J210: EQ | K210: NSE | L210: NSE
... A290: 126721 | B290: 495 | C290: BLUEDART | D290: BLUE DART EXPRESS | E290: 0 | G290: 0 | H290: 0.5 | I290: 1 | J290: EQ | K290: NSE | L290: NSE
A291: 127489 | B291: 498 | C291: 903SFL28-YI | E291: 0 | G291: 0 | H291: 0.01 | I291: 1 | J291: EQ | K291: NSE | L291: NSE | N291: blank
A292: 129793 | B292: 507 | C292: PULZ-SM | D292: PULZ ELECTRONICS | E292: 0 | G292: 0 | H292: 0.05 | I292: 2000 | J292: EQ | K292: NSE | L292: NSE
A293: 130305 | B293: 509 | C293: MAZDOCK | D293: MAZAGON DOCK SHIPBUIL | E293: 0 | G293: 0 | H293: 0.1 | I293: 1 | J293: EQ | K293: NSE | L293: NSE
A294: 131329 | B294: 513 | C294: BOMDYEING | D294: BOMBAY DYEING & MFG. CO L | E294: 0 | G294: 0 | H294: 0.01 | I294: 1 | J294: EQ | K294: NSE | L294: NSE
A295: 133633 | B295: 522 | C295: ICICIB22 | D295: ICICIPRAMC - BHARATIWIN | E295: 0 | G295: 0 | H295: 0.01 | I295: 1 | J295: EQ | K295: NSE | L295: NSE
A296: 134657 | B296: 526 | C296: BPCL | D296: BHARAT PETROLEUM CORP LT | E296: 0 | G296: 0 | H296: 0.05 | I296: 1 | J296: EQ | K296: NSE | L296: NSE
A297: 134913 | B297: 527 | C297: UTIAMC | D297: UTI ASSET MNGMT CO | E297: 0 | G297: 0 | H297: 0.05 | I297: 1 | J297: EQ | K297: NSE | L297: NSE
A298: 135681 | B298: 530 | C298: BPL | D298: BPL | E298: 0 | G298: 0 | H298: 0.01 | I298: 1 | J298: EQ | K298: NSE | L298: NSE
A299: 140033 | B299: 547 | C299: BRITANNIA | D299: BRITANNIA INDUSTRIES | E299: 0 | G299: 0 | H299: 0.5 | I299: 1 | J299: EQ | K299: NSE | L299: NSE
A300: 143105 | B300: 559 | C300: BSL | D300: BSL | E300: 0 | G300: 0 | H300: 0.01 | I300: 1 | J300: EQ | K300: NSE | L300: NSE
A301: 146689 | B301: 573 | C301: FELIX-SM | D301: FELIX INDUSTRIES | E301: 0 | G301: 0 | H301: 0.05 | I301: 500 | J301: EQ | K301: NSE | L301: NSE
A302: 147969 | B302: 578 | C302: LIKHITHA | D302: LIKHITHA INFRASTRUC | E302: 0 | G302: 0 | H302: 0.01 | I302: 1 | J302: EQ | K302: NSE | L302: NSE
A303: 149249 | B303: 583 | C303: CANFINHOME | D303: CAN FIN HOMES | E303: 0 | G303: 0 | H303: 0.05 | I303: 1 | J303: EQ | K303: NSE | L303: NSE
A304: 151041 | B304: 590 | C304: 669PN30-SG | D304: SDL PN 6.69% 2030 | E304: 0 | G304: 0 | H304: 0.01 | I304: 100 | J304: EQ | K304: NSE | L304: NSE
A305: 151297 | B305: 591 | C305: 840IRFC29-N8 | E305: 0 | G305: 0 | H305: 0.01 | I305: 1 | J305: EQ | K305: NSE | L305: NSE | N305: blank
A306: 151553 | B306: 592 | C306: GRAPHITE | D306: GRAPHITE INDIA | E306: 0 | G306: 0 | H306: 0.05 | I306: 1 | J306: EQ | K306: NSE | L306: NSE
A307: 151809 | B307: 593 | C307: 661KA30-SG | D307: SDL KA 6.61% 2030 | E307: 0 | G307: 0 | H307: 0.01 | I307: 100 | J307: EQ | K307: NSE | L307: NSE
A308: 152321 | B308: 595 | C308: CARBORUNIV | D308: CARBORUNDUM UNIVERSAL | E308: 0 | G308: 0 | H308: 0.05 | I308: 1 | J308: EQ | K308: NSE | L308: NSE
A309: 152577 | B309: 596 | C309: 663MH30-SG | D309: SDL MH 6.63% 2030 | E309: 0 | G309: 0 | H309: 0.01 | I309: 100 | J309: EQ | K309: NSE | L309: NSE
A310: 153345 | B310: 599 | C310: 645MH27-SG | D310: SDL MH 6.45% 2027 | E310: 0 | G310: 0 | H310: 0.01 | I310: 100 | J310: EQ | K310: NSE | L310: NSE
A311: 154369 | B311: 603 | C311: 865IRFC29-NA | E311: 0 | G311: 0 | H311: 0.01 | I311: 1 | J311: EQ | K311: NSE | L311: NSE | N311: blank
A312: 154881 | B312: 605 | C312: 655MH28-SG | D312: SDL MH 6.55% 2028 | E312: 0 | G312: 0 | H312: 0.01 | I312: 100 | J312: EQ | K312: NSE | L312: NSE
A313: 155905 | B313: 609 | C313: 665ML30-SG | D313: SDL ML 6.65% 2030 | E313: 0 | G313: 0 | H313: 0.01 | I313: 100 | J313: EQ | K313: NSE | L313: NSE
A314: 156417 | B314: 611 | C314: 66RJ30A-SG | D314: SDL RJ 6.6% 2030 | E314: 0 | G314: 0 | H314: 0.01 | I314: 100 | J314: EQ | K314: NSE | L314: NSE
A315: 157185 | B315: 614 | C315: 663UP30-SG | D315: SDL UP 6.63% 2030 | E315: 0 | G315: 0 | H315: 0.01 | I315: 100 | J315: EQ | K315: NSE | L315: NSE
A316: 157953 | B316: 617 | C316: 662UK30-SG | D316: SDL UK 6.62% 2030 | E316: 0 | G316: 0 | H316: 0.01 | I316: 100 | J316: EQ | K316: NSE | L316: NSE
A317: 158209 | B317: 618 | C317: 675KA33A-SG | D317: SDL KA 6.75% 2033 | E317: 0 | G317: 0 | H317: 0.01 | I317: 100 | J317: EQ | K317: NSE | L317: NSE
A318: 158465 | B318: 619 | C318: CENTENKA | D318: CENTURY ENKA | E318: 0 | G318: 0 | H318: 0.05 | I318: 1 | J318: EQ | K318: NSE | L318: NSE
A319: 158721 | B319: 620 | C319: 699WB35-SG | D319: SDL WB 6.99% 2035 | E319: 0 | G319: 0 | H319: 0.01 | I319: 100 | J319: EQ | K319: NSE | L319: NSE
A320: 160001 | B320: 625 | C320: ABREL | D320: ADITYA BIRLA REAL EST | E320: 0 | G320: 0 | H320: 0.1 | I320: 1 | J320: EQ | K320: NSE | L320: NSE
A321: 160257 | B321: 626 | C321: 691AP39-SG | D321: SDL AP 6.91% 2039 | E321: 0 | G321: 0 | H321: 0.01 | I321: 100 | J321: EQ | K321: NSE | L321: NSE
A322: 160769 | B322: 628 | C322: CESC | D322: CESC | E322: 0 | G322: 0 | H322: 0.01 | I322: 1 | J322: EQ | K322: NSE | L322: NSE
A323: 161025 | B323: 629 | C323: 691MP40-SG | D323: SDL MP 6.91% 2040 | E323: 0 | G323: 0 | H323: 0.01 | I323: 100 | J323: EQ | K323: NSE | L323: NSE
... A360: 211713 | B360: 827 | C360: DEEPAKFERT | D360: DEEPAK FERTILIZERS & PETR | E360: 0 | G360: 0 | H360: 0.1 | I360: 1 | J360: EQ | K360: NSE | L360: NSE
A361: 213505 | B361: 834 | C361: SGBOC28VII-GB | D361: 2.50%GOLDBONDS2028SR-VII | E361: 0 | G361: 0 | H361: 0.01 | I361: 1 | J361: EQ | K361: NSE | L361: NSE | M361: Yes
A362: 214017 | B362: 836 | C362: 575PY26-SG | D362: SDL PY 5.75% 2026 | E362: 0 | G362: 0 | H362: 0.01 | I362: 100 | J362: EQ | K362: NSE | L362: NSE
A363: 214273 | B363: 837 | C363: 61RJ27-SG | D363: SDL RJ 6.1% 2027 | E363: 0 | G363: 0 | H363: 0.01 | I363: 100 | J363: EQ | K363: NSE | L363: NSE
A364: 214529 | B364: 838 | C364: 645HP29-SG | D364: SDL HP 6.45% 2029 | E364: 0 | G364: 0 | H364: 0.01 | I364: 100 | J364: EQ | K364: NSE | L364: NSE
A365: 215041 | B365: 840 | C365: 651HP30-SG | D365: SDL HP 6.51% 2030 | E365: 0 | G365: 0 | H365: 0.01 | I365: 100 | J365: EQ | K365: NSE | L365: NSE
A366: 215809 | B366: 843 | C366: 64KA30B-SG | D366: SDL KA 6.4% 2030 | E366: 0 | G366: 0 | H366: 0.01 | I366: 100 | J366: EQ | K366: NSE | L366: NSE
A367: 216577 | B367: 846 | C367: 64GJ30A-SG | D367: SDL GJ 6.4% 2030 | E367: 0 | G367: 0 | H367: 0.01 | I367: 100 | J367: EQ | K367: NSE | L367: NSE
A368: 217345 | B368: 849 | C368: 642UP30-SG | D368: SDL UP 6.42% 2030 | E368: 0 | G368: 0 | H368: 0.01 | I368: 100 | J368: EQ | K368: NSE | L368: NSE
A369: 217601 | B369: 850 | C369: SMVD-ST | D369: SMVD POLY PACK | E369: 0 | G369: 0 | H369: 0.05 | I369: 4040 | J369: EQ | K369: NSE | L369: NSE
A370: 218113 | B370: 852 | C370: 642GA30-SG | D370: SDL GA 6.42% 2030 | E370: 0 | G370: 0 | H370: 0.01 | I370: 100 | J370: EQ | K370: NSE | L370: NSE
A371: 218369 | B371: 853 | C371: 644UK30-SG | D371: SDL UK 6.44% 2030 | E371: 0 | G371: 0 | H371: 0.01 | I371: 100 | J371: EQ | K371: NSE | L371: NSE
A372: 218881 | B372: 855 | C372: 645RJ30-SG | D372: SDL RJ 6.45% 2030 | E372: 0 | G372: 0 | H372: 0.01 | I372: 100 | J372: EQ | K372: NSE | L372: NSE
A373: 219393 | B373: 857 | C373: DHAMPURSUG | D373: DHAMPUR SUGAR MILLS | E373: 0 | G373: 0 | H373: 0.01 | I373: 1 | J373: EQ | K373: NSE | L373: NSE
... A410: 256001 | B410: 1000 | C410: 656MH32-SG | D410: SDL MH 6.56% 2032 | E410: 0 | G410: 0 | H410: 0.01 | I410: 100 | J410: EQ | K410: NSE | L410: NSE
A411: 256257 | B411: 1001 | C411: 94SFL28-YL | E411: 0 | G411: 0 | H411: 0.01 | I411: 1 | J411: EQ | K411: NSE | L411: NSE | N411: blank
A412: 257025 | B412: 1004 | C412: 679AP34-SG | D412: SDL AP 6.79% 2034 | E412: 0 | G412: 0 | H412: 0.01 | I412: 100 | J412: EQ | K412: NSE | L412: NSE
A413: 257537 | B413: 1006 | C413: 675KA35-SG | D413: SDL KA 6.75% 2035 | E413: 0 | G413: 0 | H413: 0.01 | I413: 100 | J413: EQ | K413: NSE | L413: NSE
A414: 257793 | B414: 1007 | C414: 679PN35-SG | D414: SDL PN 6.79% 2035 | E414: 0 | G414: 0 | H414: 0.01 | I414: 100 | J414: EQ | K414: NSE | L414: NSE
A415: 258049 | B415: 1008 | C415: FACT | D415: FACT | E415: 0 | G415: 0 | H415: 0.05 | I415: 1 | J415: EQ | K415: NSE | L415: NSE
A416: 258305 | B416: 1009 | C416: 68JK35-SG | D416: SDL JK 6.8% 2035 | E416: 0 | G416: 0 | H416: 0.01 | I416: 100 | J416: EQ | K416: NSE | L416: NSE
A417: 258817 | B417: 1011 | C417: SCHAEFFLER | D417: SCHAEFFLER INDIA | E417: 0 | G417: 0 | H417: 0.1 | I417: 1 | J417: EQ | K417: NSE | L417: NSE
A418: 259073 | B418: 1012 | C418: 676MP40-SG | D418: SDL MP 6.76% 2040 | E418: 0 | G418: 0 | H418: 0.01 | I418: 100 | J418: EQ | K418: NSE | L418: NSE
A419: 259841 | B419: 1015 | C419: 688WB40-SG | D419: SDL WB 6.88% 2040 | E419: 0 | G419: 0 | H419: 0.01 | I419: 100 | J419: EQ | K419: NSE | L419: NSE
...

Sheet zerodhaNSEname
A1: instrument_token | B1: exchange_token | C1: tradingsymbol | D1: name
A2: 1025 | B2: 4 | C2: 21STCENMGM | D2: 21ST CENTURY MGMT SERVICE
A3: 1793 | B3: 7 | C3: AARTIIND | D3: AARTI INDUSTRIES
A4: 3329 | B4: 13 | C4: ABB | D4: ABB INDIA
A5: 4353 | B5: 17 | C5: GATECHDVR | D5: GACM TECHNOLOGIES
A6: 4865 | B6: 19 | C6: STYRENIX | D6: STYRENIX PERFORMANCE
A7: 5633 | B7: 22 | C7: ACC | D7: ACC
A8: 6401 | B8: 25 | C8: ADANIENT | D8: ADANI ENTERPRISES
A9: 8705 | B9: 34 | C9: ADOR | D9: ADOR WELDING
A10: 10241 | B10: 40 | C10: AEGISLOG | D10: AEGIS LOGISTICS
A11: 11777 | B11: 46 | C11: SANWARIA-BZ | D11: SANWARIA CONSUMER
A12: 12289 | B12: 48 | C12: HAPPSTMNDS | D12: HAPPIEST MINDS TECHNO
A13: 20225 | B13: 79 | C13: ALEMBICLTD | D13: ALEMBIC
... A2683: 268041 | B2683: 1047 | C2683: NIFTY 500 | D2683: NIFTY 500

Sheet F&O list
A1: SL NO | B1: F&O STOCKS NAME | C1: SYMBOL | D1: LOT SIZE | E1: zerodha name
A2: 1 | B2: Nifty Bank | C2: BANKNIFTY | D2: 30 | E2: NIFTY BANK
A3: 2 | B3: Finnifty | C3: FINNIFTY | D3: 60 | E3: NIFTY FIN SERVICE
A4: 3 | B4: Nifty Midcap Select | C4: MIDCPNIFTY | D4: 120 | E4: NIFTY MIDCAP SELECT (MIDCPNIFTY)
A5: 4 | B5: Nifty 50 | C5: NIFTY | D5: 65 | E5: NIFTY 50
A6: 5 | B6: Nifty Next 50 | C6: NIFTY NEXT 50 | D6: 25 | E6: NIFTY NEXT 50
A7: 6 | B7: 360 One WAM | C7: 360ONE | D7: 500 | E7: =VLOOKUP(C7,zerodhaNSEname!C:D,2,0) -> 360 ONE WAM
A8: 7 | B8: ABB | C8: ABB | D8: 125 | E8: =VLOOKUP(C8,zerodhaNSEname!C:D,2,0) -> ABB INDIA
A9: 8 | B9: Aditya Birla Capital | C9: ABCAPITAL | D9: 3100 | E9: =VLOOKUP(C9,zerodhaNSEname!C:D,2,0) -> ADITYA BIRLA CAPITAL
A10: 9 | B10: Adani Energy Solutions | C10: ADANIENSOL | D10: 675 | E10: =VLOOKUP(C10,zerodhaNSEname!C:D,2,0) -> ADANI ENERGY SOLUTION
A11: 10 | B11: Adani Enterprises | C11: ADANIENT | D11: 300 | E11: =VLOOKUP(C11,zerodhaNSEname!C:D,2,0) -> ADANI ENTERPRISES
A12: 11 | B12: Adani Green Energy | C12: ADANIGREEN | D12: 600 | E12: =VLOOKUP(C12,zerodhaNSEname!C:D,2,0) -> ADANI GREEN ENERGY
A13: 12 | B13: Adani Ports & SEZ | C13: ADANIPORTS | D13: 475 | E13: =VLOOKUP(C13,zerodhaNSEname!C:D,2,0) -> ADANI PORT & SEZ
A14: 13 | B14: Alkem Laboratories | C14: ALKEM | D14: 125 | E14: =VLOOKUP(C14,zerodhaNSEname!C:D,2,0) -> ALKEM LABORATORIES
A15: 14 | B15: Amber Enterprises | C15: AMBER | D15: 100 | E15: =VLOOKUP(C15,zerodhaNSEname!C:D,2,0) -> AMBER ENTERPRISES (I)
A16: 15 | B16: Ambuja Cements | C16: AMBUJACEM | D16: 1050 | E16: =VLOOKUP(C16,zerodhaNSEname!C:D,2,0) -> AMBUJA CEMENTS
A17: 16 | B17: Angel One | C17: ANGELONE | D17: 250 | E17: =VLOOKUP(C17,zerodhaNSEname!C:D,2,0) -> ANGEL ONE
A18: 17 | B18: APL Apollo Tubes | C18: APLAPOLLO | D18: 350 | E18: =VLOOKUP(C18,zerodhaNSEname!C:D,2,0) -> APL APOLLO TUBES
... A191: 190 | B191: Tata Elxsi | C191: TATAELXSI | D191: 100 | E191: =VLOOKUP(C191,zerodhaNSEname!C:D,2,0) -> TATA ELXSI
A192: 191 | B192: Tata Motors | C192: TATAMOTORS | D192: 800 | E192: TATA MOTORS PASS VEH
A193: 192 | B193: Tata Power | C193: TATAPOWER | D193: 1450 | E193: =VLOOKUP(C193,zerodhaNSEname!C:D,2,0) -> TATA POWER CO
A194: 193 | B194: Tata Steel | C194: TATASTEEL | D194: 5500 | E194: =VLOOKUP(C194,zerodhaNSEname!C:D,2,0) -> TATA STEEL
A195: 194 | B195: Tata Technologies | C195: TATATECH | D195: 800 | E195: =VLOOKUP(C195,zerodhaNSEname!C:D,2,0) -> TATA TECHNOLOGIES
A196: 195 | B196: Tata Consultancy Services | C196: TCS | D196: 175 | E196: =VLOOKUP(C196,zerodhaNSEname!C:D,2,0) -> TATA CONSULTANCY SERV LT
A197: 196 | B197: Tech Mahindra | C197: TECHM | D197: 600 | E197: =VLOOKUP(C197,zerodhaNSEname!C:D,2,0) -> TECH MAHINDRA
A198: 197 | B198: Tube Investment | C198: TIINDIA | D198: 200 | E198: =VLOOKUP(C198,zerodhaNSEname!C:D,2,0) -> TUBE INVEST OF INDIA
A199: 198 | B199: Titagarh Rail Systems | C199: TITAGARH | D199: 725 | E199: =VLOOKUP(C199,zerodhaNSEname!C:D,2,0) -> TITAGARH RAIL SYSTEMS
A200: 199 | B200: Titan | C200: TITAN | D200: 175 | E200: =VLOOKUP(C200,zerodhaNSEname!C:D,2,0) -> TITAN COMPANY
A201: 200 | B201: Torrent Pharmaceuticals | C201: TORNTPHARM | D201: 250 | E201: =VLOOKUP(C201,zerodhaNSEname!C:D,2,0) -> TORRENT PHARMACEUTICALS L
A202: 201 | B202: Torrent Power | C202: TORNTPOWER | D202: 375 | E202: =VLOOKUP(C202,zerodhaNSEname!C:D,2,0) -> TORRENT POWER
A203: 202 | B203: Trent | C203: TRENT | D203: 100 | E203: =VLOOKUP(C203,zerodhaNSEname!C:D,2,0) -> TRENT
A204: 203 | B204: TVS Motors | C204: TVSMOTOR | D204: 350 | E204: =VLOOKUP(C204,zerodhaNSEname!C:D,2,0) -> TVS MOTOR COMPANY
... A215: 214 | B215: Zydus Life Science | C215: ZYDUSLIFE | D215: 900 | E215: =VLOOKUP(C215,zerodhaNSEname!C:D,2,0) -> ZYDUS LIFESCIENCES
